MANIFEST.in
requirements.txt
setup.py
test_requirements.txt
version.txt
cloudshell/__init__.py
cloudshell/networking/__init__.py
cloudshell/networking/brocade/__init__.py
cloudshell/networking/brocade/brocade_configuration_operations.py
cloudshell/networking/brocade/brocade_connectivity_operations.py
cloudshell/networking/brocade/brocade_firmware_operations.py
cloudshell/networking/brocade/brocade_send_command_operations.py
cloudshell/networking/brocade/brocade_state_operations.py
cloudshell/networking/brocade/autoload/__init__.py
cloudshell/networking/brocade/autoload/brocade_snmp_autoload.py
cloudshell/networking/brocade/mibs/BROCADE-ENTITY-OID-MIB.py
cloudshell/networking/brocade/mibs/FOUNDRY-SN-ROOT-MIB.py
cloudshell/networking/brocade/mibs/__init__.py
cloudshell/tests/__init__.py
cloudshell/tests/networking_brocade_tests.py
cloudshell/tests/test_brocade_connectivity_operations.py
cloudshell/tests/test_brocade_firmware_operations.py
cloudshell_networking_brocade.egg-info/PKG-INFO
cloudshell_networking_brocade.egg-info/SOURCES.txt
cloudshell_networking_brocade.egg-info/dependency_links.txt
cloudshell_networking_brocade.egg-info/requires.txt
cloudshell_networking_brocade.egg-info/top_level.txt