Metadata-Version: 1.0
Name: cloudshell-networking-brocade
Version: 1.0.9
Summary: QualiSystems Brocade package
Home-page: http://www.qualisystems.com/
Author: QualiSystems
Author-email: info@qualisystems.com
License: UNKNOWN
Platform: UNKNOWN
